gemini_rotator/__init__.py
gemini_rotator/py.typed
gemini_rotator-0.1.0.dist-info/METADATA
gemini_rotator-0.1.0.dist-info/WHEEL
gemini_rotator-0.1.0.dist-info/RECORD
