Metadata-Version: 2.4
Name: gemini-rotator
Version: 0.1.0
Summary: Key rotator, don't get dizzy.
Author-email: johnmalek312 <77510343+johnmalek312@users.noreply.github.com>
Requires-Python: >=3.9
Requires-Dist: google-auth
